regionate/__init__.py
regionate/boundaries.py
regionate/grid_conform.py
regionate/integrate.py
regionate/overlaps.py
regionate/region.py
regionate/regions.py
regionate/utilities.py
regionate/version.py
regionate/tests/test_gridded_regions.py
regionate-0.5.1.dist-info/METADATA
regionate-0.5.1.dist-info/WHEEL
regionate-0.5.1.dist-info/licenses/LICENSE
regionate-0.5.1.dist-info/RECORD
